tf_neural_style_transfer/__init__.py
tf_neural_style_transfer/execute.py
tf_neural_style_transfer-0.1.0.dist-info/METADATA
tf_neural_style_transfer-0.1.0.dist-info/WHEEL
tf_neural_style_transfer-0.1.0.dist-info/RECORD
